sayaka-0.7.0.dist-info/METADATA
sayaka-0.7.0.dist-info/WHEEL
sayaka-0.7.0.dist-info/licenses/LICENSE
sayaka.libs/libgcc_s-98a1ef30.so.1
sayaka/__init__.py
sayaka/py.typed
sayaka/sayaka.cpython-314-x86_64-linux-musl.so
sayaka/sayaka.pyi
sayaka-0.7.0.dist-info/RECORD
