Metadata-Version: 2.4
Name: sayaka
Version: 0.7.0
Classifier: Programming Language :: Rust
Classifier: Programming Language :: Python :: Implementation :: CPython
License-File: LICENSE
Summary: A Rust-backed Python module for decrypting and decompressing data for an anime game.
Author-email: baiqwerdvd <baiqwerdvd@gmail.com>
License: MIT
Requires-Python: >=3.10, <3.15
Project-URL: Homepage, https://github.com/baiqwerdvd/sayaka
Project-URL: Repository, https://github.com/baiqwerdvd/sayaka
